RustMann-0.1.0.dist-info/METADATA
RustMann-0.1.0.dist-info/WHEEL
RustMann/Tensor.py
RustMann/Mann.py
RustMann/__init__.py
RustMann/RustMann.cpython-36m-x86_64-linux-gnu.so
RustMann-0.1.0.dist-info/RECORD
