Metadata-Version: 2.1
Name: RustMann
Version: 0.1.0
Classifier: Programming Language :: Rust
Classifier: Programming Language :: Python :: Implementation :: CPython
Classifier: Programming Language :: Python :: Implementation :: PyPy
Requires-Dist: numpy>=1.19.2
Requires-Dist: matplotlib>=3
Requires-Dist: tqdm>=4
Requires-Dist: pydantic>=1.9.0
Requires-Python: >=3.6
